mmcif/__init__.py
mmcif/core/__init__.py
mmcif/core/mmciflib.cpython-312-darwin.so
mmcif/io/BinaryCifReader.py
mmcif/io/BuildDictionaryExec.py
mmcif/io/IoAdapterCore.py
mmcif/io/BinaryCifWriter.py
mmcif/io/CifFile.py
mmcif/io/__init__.py
mmcif/io/IoAdapterPy.py
mmcif/io/PdbxReader.py
mmcif/io/IoAdapterBase.py
mmcif/io/PdbxWriter.py
mmcif/io/PdbxExceptions.py
mmcif/api/DictionaryApi.py
mmcif/api/PdbxContainers.py
mmcif/api/MethodUtils.py
mmcif/api/DataCategoryBase.py
mmcif/api/DictionaryInclude.py
mmcif/api/__init__.py
mmcif/api/DataCategoryTyped.py
mmcif/api/DictMethodRunner.py
mmcif/api/Method.py
mmcif/api/DataCategory.py
mmcif/api/DataCategoryFormatted.py
mmcif-1.0.0.dist-info/RECORD
mmcif-1.0.0.dist-info/WHEEL
mmcif-1.0.0.dist-info/entry_points.txt
mmcif-1.0.0.dist-info/top_level.txt
mmcif-1.0.0.dist-info/METADATA
mmcif-1.0.0.dist-info/licenses/LICENSE
