Metadata-Version: 2.4
Name: mmcif
Version: 1.0.0
Summary: mmCIF Core Access Library
Author-email: John Westbrook <john.westbrook@rcsb.org>
License: Apache-2.0
Project-URL: Homepage, https://mmcif.wwpdb.org
Project-URL: Repository, https://github.com/rcsb/py-mmcif
Classifier: Programming Language :: Python
Classifier: Programming Language :: Python :: 3
Classifier: Programming Language :: Python :: 3.8
Classifier: Programming Language :: Python :: 3.9
Classifier: Programming Language :: Python :: 3.10
Classifier: Programming Language :: Python :: 3.11
Classifier: Programming Language :: Python :: 3.12
Classifier: Programming Language :: Python :: 3.13
Classifier: Programming Language :: Python :: 3.14
Classifier: Development Status :: 5 - Production/Stable
Classifier: Intended Audience :: Developers
Classifier: Natural Language :: English
Requires-Python: >=3.6
License-File: LICENSE
Requires-Dist: requests>=2.25
Requires-Dist: msgpack
Provides-Extra: test
Requires-Dist: tox; extra == "test"
Requires-Dist: coverage; extra == "test"
Provides-Extra: docs
Requires-Dist: tox; extra == "docs"
Requires-Dist: coverage; extra == "docs"
Requires-Dist: mkdocs; extra == "docs"
Requires-Dist: mkdocstrings[python-legacy]>=0.18; extra == "docs"
Requires-Dist: mkdocs-material; extra == "docs"
Requires-Dist: markdown-include; extra == "docs"
Requires-Dist: pymdown-extensions; extra == "docs"
Requires-Dist: mkdocs-material-extensions; extra == "docs"
Provides-Extra: all
Requires-Dist: tox; extra == "all"
Requires-Dist: coverage; extra == "all"
Dynamic: license-file
